{"__symbolic":"module","version":4,"metadata":{"NGX_YTD_API_DEFAULT_STANDARD_PARAMS":{"__symbolic":"new","expression":{"__symbolic":"reference","module":"@angular/core","name":"InjectionToken","line":4,"character":55},"arguments":["ngx-ytd-api-default-standard-params"]},"NGX_YTD_API_DEFAULT_STANDARD_OPTIONS":{"__symbolic":"reference","name":"NGX_YTD_API_DEFAULT_STANDARD_PARAMS"},"NgxYtdApiStandardParams":{"__symbolic":"interface"},"NgxYtdApiStandardOpts":{"__symbolic":"interface"},"NgxYtdApiStandardWithPartParams":{"__symbolic":"interface"},"NgxYtdApiGenericOpts":{"__symbolic":"interface"},"NgxYtdApiGenericResource":{"__symbolic":"interface"},"NgxYtdApiGenericResponse":{"__symbolic":"interface"},"NgxYtdApiCommonModule":{"__symbolic":"class","decorators":[{"__symbolic":"call","expression":{"__symbolic":"reference","module":"@angular/core","name":"NgModule","line":4,"character":1},"arguments":[{"imports":[{"__symbolic":"reference","module":"ngx-simple-http","name":"SimpleHttpModule","line":6,"character":4}],"providers":[{"__symbolic":"reference","name":"NgxYtdApiCommonService"}]}]}],"members":{}},"NgxYtdApiCommonService":{"__symbolic":"class","decorators":[{"__symbolic":"call","expression":{"__symbolic":"reference","module":"@angular/core","name":"Injectable","line":7,"character":1}}],"members":{"__ctor__":[{"__symbolic":"constructor","parameterDecorators":[null,[{"__symbolic":"call","expression":{"__symbolic":"reference","module":"@angular/core","name":"Inject","line":11,"character":5},"arguments":[{"__symbolic":"reference","name":"NGX_YTD_API_DEFAULT_STANDARD_OPTIONS"}]},{"__symbolic":"call","expression":{"__symbolic":"reference","module":"@angular/core","name":"Optional","line":11,"character":51}}]],"parameters":[{"__symbolic":"reference","module":"ngx-simple-http","name":"SimpleHttpService","line":10,"character":18},{"__symbolic":"reference","name":"NgxYtdApiStandardParams"}]}],"keyValueExistsAndNonNull":[{"__symbolic":"method"}],"mergeOpts":[{"__symbolic":"method"}],"mergeParamsWithStandardParams":[{"__symbolic":"method"}],"sendHttpRequest":[{"__symbolic":"method"}]}}},"origins":{"NGX_YTD_API_DEFAULT_STANDARD_PARAMS":"./ytd-api-common.injectors","NGX_YTD_API_DEFAULT_STANDARD_OPTIONS":"./ytd-api-common.injectors","NgxYtdApiStandardParams":"./ytd-api-common.interface","NgxYtdApiStandardOpts":"./ytd-api-common.interface","NgxYtdApiStandardWithPartParams":"./ytd-api-common.interface","NgxYtdApiGenericOpts":"./ytd-api-common.interface","NgxYtdApiGenericResource":"./ytd-api-common.interface","NgxYtdApiGenericResponse":"./ytd-api-common.interface","NgxYtdApiCommonModule":"./ytd-api-common.module","NgxYtdApiCommonService":"./ytd-api-common.service"},"importAs":"ngx-ytd-api/common"}